{
  "name": "Azure Cognitive Search",
  "description": null,

  "pages": [
    {
      "name": "Azure Cognitive Search",
      "description": null,
      "widgets": [
        {
          "title": "Summary",
          "layout": {
            "column": 1,
            "row": 1,
            "width": 7,
            "height": 3
          },
          "linkedEntityGuids": null,
          "visualization": {
            "id": "viz.billboard"
          },
          "rawConfiguration": {
            "dataFormatters": [],
            "facet": {
              "showOtherSeries": false
            },
            "nrqlQueries": [
              {
                "accountIds": [],
                "query": "FROM Metric SELECT AVERAGE(azure.search.searchservices.SearchLatency) AS 'Average Search Latency', AVERAGE(azure.search.searchservices.SearchQueriesPerSecond) AS 'Average Search Queries Per Second', SUM(azure.search.searchservices.DocumentsProcessedCount) AS 'Total Number of Documents Processed', SUM(azure.search.searchservices.SkillExecutionCount) AS 'Total Number of Skill Executions' WHERE collector.name = 'azure-monitor' AND azure.resourceType = 'microsoft.search/searchservices'"
              }
            ],
            "platformOptions": {
              "ignoreTimeRange": false
            }
          }
        },
        {
          "title": "",
          "layout": {
            "column": 8,
            "row": 1,
            "width": 5,
            "height": 3
          },
          "linkedEntityGuids": null,
          "visualization": {
            "id": "viz.markdown"
          },
          "rawConfiguration": {
            "text": "# Azure Cognitive Search\nAzure Cognitive Search (formerly known as \"Azure Search\") is a cloud search service that gives developers infrastructure, APIs and tools for building a rich search experience over private, heterogeneous content in web, mobile and enterprise applications."
          }
        },
        {
          "title": "Search latency",
          "layout": {
            "column": 1,
            "row": 4,
            "width": 4,
            "height": 3
          },
          "linkedEntityGuids": null,
          "visualization": {
            "id": "viz.line"
          },
          "rawConfiguration": {
            "facet": {
              "showOtherSeries": false
            },
            "legend": {
              "enabled": true
            },
            "nrqlQueries": [
              {
                "accountIds": [],
                "query": "FROM Metric SELECT AVERAGE(azure.search.searchservices.SearchLatency) AS 'Average Search Latency' WHERE collector.name = 'azure-monitor' AND azure.resourceType = 'microsoft.search/searchservices' TIMESERIES AUTO"
              }
            ],
            "platformOptions": {
              "ignoreTimeRange": false
            },
            "units": {
              "unit": "SECONDS"
            },
            "yAxisLeft": {
              "zero": true
            }
          }
        },
        {
          "title": "Search queries per second",
          "layout": {
            "column": 5,
            "row": 4,
            "width": 4,
            "height": 3
          },
          "linkedEntityGuids": null,
          "visualization": {
            "id": "viz.line"
          },
          "rawConfiguration": {
            "facet": {
              "showOtherSeries": false
            },
            "legend": {
              "enabled": true
            },
            "nrqlQueries": [
              {
                "accountIds": [],
                "query": "FROM Metric SELECT AVERAGE(azure.search.searchservices.SearchQueriesPerSecond) AS 'Average Search Queries Per Second' WHERE collector.name = 'azure-monitor' AND azure.resourceType = 'microsoft.search/searchservices' TIMESERIES AUTO"
              }
            ],
            "platformOptions": {
              "ignoreTimeRange": false
            },
            "units": {
              "unit": "COUNT"
            },
            "yAxisLeft": {
              "zero": true
            }
          }
        },
        {
          "title": "Throttled search queries percentage",
          "layout": {
            "column": 9,
            "row": 4,
            "width": 4,
            "height": 3
          },
          "linkedEntityGuids": null,
          "visualization": {
            "id": "viz.line"
          },
          "rawConfiguration": {
            "facet": {
              "showOtherSeries": false
            },
            "legend": {
              "enabled": true
            },
            "nrqlQueries": [
              {
                "accountIds": [],
                "query": "FROM Metric SELECT AVERAGE(azure.search.searchservices.ThrottledSearchQueriesPercentage) AS 'Average Throttled Search Queries Percentage' WHERE collector.name = 'azure-monitor' AND azure.resourceType = 'microsoft.search/searchservices' TIMESERIES AUTO"
              }
            ],
            "platformOptions": {
              "ignoreTimeRange": false
            },
            "units": {
              "unit": "PERCENTAGE"
            },
            "yAxisLeft": {
              "zero": true
            }
          }
        },
        {
          "title": "Number of documents processed",
          "layout": {
            "column": 1,
            "row": 7,
            "width": 6,
            "height": 3
          },
          "linkedEntityGuids": null,
          "visualization": {
            "id": "viz.line"
          },
          "rawConfiguration": {
            "facet": {
              "showOtherSeries": false
            },
            "legend": {
              "enabled": true
            },
            "nrqlQueries": [
              {
                "accountIds": [],
                "query": "FROM Metric SELECT SUM(azure.search.searchservices.DocumentsProcessedCount) AS 'Total Number of Documents Processed' WHERE collector.name = 'azure-monitor' AND azure.resourceType = 'microsoft.search/searchservices' FACET azure.search.searchservices.DataSourceName TIMESERIES AUTO"
              }
            ],
            "platformOptions": {
              "ignoreTimeRange": false
            },
            "units": {
              "unit": "COUNT"
            },
            "yAxisLeft": {
              "zero": true
            }
          }
        },
        {
          "title": "Number of skill executions",
          "layout": {
            "column": 7,
            "row": 7,
            "width": 6,
            "height": 3
          },
          "linkedEntityGuids": null,
          "visualization": {
            "id": "viz.line"
          },
          "rawConfiguration": {
            "facet": {
              "showOtherSeries": false
            },
            "legend": {
              "enabled": true
            },
            "nrqlQueries": [
              {
                "accountIds": [],
                "query": "FROM Metric SELECT SUM(azure.search.searchservices.SkillExecutionCount) AS 'Total Number of Skill Executions' WHERE collector.name = 'azure-monitor' AND azure.resourceType = 'microsoft.search/searchservices' FACET azure.search.searchservices.SkillType TIMESERIES AUTO"
              }
            ],
            "platformOptions": {
              "ignoreTimeRange": false
            },
            "yAxisLeft": {
              "zero": true
            }
          }
        }
      ]
    }
  ],
  "variables": []
}